pluxee/__init__.py
pluxee/aia_chaser.py
pluxee/base_pluxee_client.py
pluxee/exceptions.py
pluxee/pluxee_async_client.py
pluxee/pluxee_client.py
pluxee/py.typed
pluxee_api-0.2.2.dist-info/licenses/LICENSE
pluxee_api-0.2.2.dist-info/METADATA
pluxee_api-0.2.2.dist-info/WHEEL
pluxee_api-0.2.2.dist-info/top_level.txt
pluxee_api-0.2.2.dist-info/RECORD
