Metadata-Version: 2.4
Name: pluxee-api
Version: 0.2.2
Summary: An unofficial python API to access Pluxee (Sodexo) balance and transactions
Author: Thibaut Capuano
Maintainer: Thibaut Capuano
Project-URL: Homepage, https://github.com/Tib612/pluxee-api
Project-URL: Issues, https://github.com/Tib612/pluxee-api/issues
Project-URL: Documentation, https://pluxee-api.readthedocs.io/en/latest/
Keywords: pluxee,sodexo,api,scraping
Classifier: Development Status :: 3 - Alpha
Classifier: Intended Audience :: Developers
Classifier: Operating System :: OS Independent
Classifier: Programming Language :: Python :: 3
Classifier: Programming Language :: Python :: 3 :: Only
Classifier: Programming Language :: Python :: 3.7
Classifier: Programming Language :: Python :: 3.8
Classifier: Programming Language :: Python :: 3.9
Classifier: Programming Language :: Python :: 3.10
Classifier: Programming Language :: Python :: 3.11
Classifier: Programming Language :: Python :: 3.12
License-File: LICENSE
Requires-Dist: requests
Requires-Dist: beautifulsoup4
Requires-Dist: pyopenssl
Requires-Dist: cryptography
Requires-Dist: certifi
Provides-Extra: dev
Requires-Dist: tox; extra == "dev"
Requires-Dist: flake8; extra == "dev"
Requires-Dist: mypy; extra == "dev"
Requires-Dist: pytest; extra == "dev"
Requires-Dist: types-requests; extra == "dev"
Requires-Dist: pytest-mock; extra == "dev"
Requires-Dist: pytest-xdist; extra == "dev"
Requires-Dist: pytest-cov; extra == "dev"
Requires-Dist: pre-commit; extra == "dev"
Requires-Dist: pants; extra == "dev"
Requires-Dist: types-beautifulsoup4; extra == "dev"
Requires-Dist: build; extra == "dev"
Requires-Dist: pytest-asyncio; extra == "dev"
Provides-Extra: async
Requires-Dist: aiohttp; extra == "async"
Provides-Extra: doc
Requires-Dist: sphinx; extra == "doc"
Dynamic: license-file
